search_engine_tool_vito1317/__init__.py
search_engine_tool_vito1317/search_engine_tool.py
search_engine_tool_vito1317/engine/__init__.py
search_engine_tool_vito1317/engine/bing.py
search_engine_tool_vito1317/engine/google.py
search_engine_tool_vito1317/engine/yahoo.py
search_engine_tool_vito1317-0.7.0.dist-info/LICENSE
search_engine_tool_vito1317-0.7.0.dist-info/METADATA
search_engine_tool_vito1317-0.7.0.dist-info/WHEEL
search_engine_tool_vito1317-0.7.0.dist-info/top_level.txt
search_engine_tool_vito1317-0.7.0.dist-info/RECORD
