Metadata-Version: 2.1
Name: search-engine-tool-vito1317
Version: 0.7.0
Summary: 搜索引擎API Bing / Google / Yahoo 
Home-page: https://github.com/vito1317/search-engine-tool-vito1317
Author: vito
Author-email: vito95311@gmail.com
License: MIT
Classifier: Development Status :: 3 - Alpha
Classifier: Intended Audience :: Developers
Classifier: License :: OSI Approved :: MIT License
Classifier: Programming Language :: Python
Classifier: Programming Language :: Python :: 3
Classifier: Programming Language :: Python :: 3.11
License-File: LICENSE
Requires-Dist: selenium
Requires-Dist: BeautifulSoup4
